passacre/__init__.py
passacre/__main__.py
passacre/_argparse.py
passacre/_backend_capnp.py
passacre/_jsonmini.py
passacre/_ometa.py
passacre/_ordereddict.py
passacre/_passacre.capnp
passacre/_version.py
passacre/application.py
passacre/compat.py
passacre/completion.py
passacre/config.py
passacre/features.py
passacre/generator.py
passacre/jsonmini.py
passacre/multibase.py
passacre/schema.py
passacre/schema.sql
passacre/util.py
passacre/yaml2sqlite.py
passacre/test/__init__.py
passacre/test/test_application.py
passacre/test/test_compat.py
passacre/test/test_completion.py
passacre/test/test_config.py
passacre/test/test_generator.py
passacre/test/test_jsonmini.py
passacre/test/test_multibase.py
passacre/test/test_schema.py
passacre/test/data/always-confirm.sqlite
passacre/test/data/always-hash.sqlite
passacre/test/data/keccak.sqlite
passacre/test/data/keccak.yaml
passacre/test/data/no-words.sqlite
passacre/test/data/nonextant-words.sqlite
passacre/test/data/skein.sqlite
passacre/test/data/skein.yaml
passacre/test/data/words
passacre/test/data/words2
passacre/test/data/json/fail10.jtest
passacre/test/data/json/fail11.jtest
passacre/test/data/json/fail12.jtest
passacre/test/data/json/fail13.jtest
passacre/test/data/json/fail14.jtest
passacre/test/data/json/fail15.jtest
passacre/test/data/json/fail16.jtest
passacre/test/data/json/fail17.jtest
passacre/test/data/json/fail19.jtest
passacre/test/data/json/fail2.jtest
passacre/test/data/json/fail20.jtest
passacre/test/data/json/fail21.jtest
passacre/test/data/json/fail22.jtest
passacre/test/data/json/fail24.jtest
passacre/test/data/json/fail25.jtest
passacre/test/data/json/fail26.jtest
passacre/test/data/json/fail27.jtest
passacre/test/data/json/fail28.jtest
passacre/test/data/json/fail32.jtest
passacre/test/data/json/fail33.jtest
passacre/test/data/json/fail4.jtest
passacre/test/data/json/fail5.jtest
passacre/test/data/json/fail6.jtest
passacre_nobackend-0.16.1.2.dist-info/DESCRIPTION.rst
passacre_nobackend-0.16.1.2.dist-info/METADATA
passacre_nobackend-0.16.1.2.dist-info/RECORD
passacre_nobackend-0.16.1.2.dist-info/WHEEL
passacre_nobackend-0.16.1.2.dist-info/entry_points.txt
passacre_nobackend-0.16.1.2.dist-info/metadata.json
passacre_nobackend-0.16.1.2.dist-info/top_level.txt
