Metadata-Version: 2.0
Name: passacre-nobackend
Version: 0.16.1.2
Summary: better repeatable password generation
Home-page: https://github.com/habnabit/passacre
Author: Aaron Gallagher
Author-email: _@habnab.it
License: ISC
Platform: UNKNOWN
Classifier: Development Status :: 2 - Pre-Alpha
Classifier: Environment :: Console
Classifier: Intended Audience :: End Users/Desktop
Classifier: License :: OSI Approved :: ISC License (ISCL)
Classifier: Operating System :: OS Independent
Classifier: Programming Language :: Python :: 2
Classifier: Programming Language :: Python :: 2.6
Classifier: Programming Language :: Python :: 2.7
Classifier: Programming Language :: Python :: 3
Classifier: Programming Language :: Python :: 3.3
Classifier: Programming Language :: Python :: 3.4
Classifier: Programming Language :: Python :: 3.5
Classifier: Topic :: Security
Requires-Dist: pycapnp
Requires-Dist: subprocess32; python_version < "3.2"
Provides-Extra: all
Requires-Dist: PyYAML; extra == 'all'
Requires-Dist: xerox; extra == 'all'
Requires-Dist: ykpers-cffi; extra == 'all'
Provides-Extra: clipboard
Requires-Dist: xerox; extra == 'clipboard'
Provides-Extra: keccak
Provides-Extra: skein
Provides-Extra: yaml
Requires-Dist: PyYAML; extra == 'yaml'
Provides-Extra: yubikey
Requires-Dist: ykpers-cffi; extra == 'yubikey'
